parityos/__init__.py
parityos/constants.py
parityos/device_connectivity.py
parityos/api_interface/__init__.py
parityos/api_interface/authentication.py
parityos/api_interface/client.py
parityos/api_interface/exceptions.py
parityos/api_interface/run_info.py
parityos/base/__init__.py
parityos/base/bit.py
parityos/base/circuit.py
parityos/base/constraint.py
parityos/base/exceptions.py
parityos/base/io_utils.py
parityos/base/operator_polynomial.py
parityos/base/operator_product.py
parityos/base/problem_representation.py
parityos/base/services.py
parityos/base/state.py
parityos/base/utils.py
parityos/base/operators/__init__.py
parityos/base/operators/conditional_operator.py
parityos/base/operators/controlled_operator.py
parityos/base/operators/measure.py
parityos/base/operators/operator.py
parityos/base/operators/rotation_operator.py
parityos/encodings/__init__.py
parityos/encodings/parity_decoder.py
parityos/encodings/parity_mapping.py
parityos_addons/__init__.py
parityos_addons/exporters/__init__.py
parityos_addons/exporters/exporter.py
parityos_addons/exporters/openqasm_exporter.py
parityos_addons/exporters/qiskit_exporter.py
typings/symengine/__init__.pyi
typings/symengine/lib/__init__.pyi
typings/symengine/lib/symengine_wrapper.pyi
parityos-3.0.0.dist-info/License.txt
parityos-3.0.0.dist-info/METADATA
parityos-3.0.0.dist-info/WHEEL
parityos-3.0.0.dist-info/top_level.txt
parityos-3.0.0.dist-info/RECORD
