Metadata-Version: 2.2
Name: parityos
Version: 3.0.0
Summary: Python bindings to the ParityOS API
Home-page: https://parityqc.com/
Requires-Python: >=3.9
License-File: License.txt
Requires-Dist: attrs
Requires-Dist: cattrs
Requires-Dist: pytest
Requires-Dist: requests
Requires-Dist: symengine
Requires-Dist: typing_extensions>=4.10.0
Provides-Extra: cirq
Requires-Dist: cirq-core; extra == "cirq"
Provides-Extra: qiskit
Requires-Dist: qiskit; extra == "qiskit"
Provides-Extra: spinz
Requires-Dist: sympy; extra == "spinz"
Provides-Extra: all
Requires-Dist: cirq-core; extra == "all"
Requires-Dist: qiskit; extra == "all"
Requires-Dist: sympy; extra == "all"
Provides-Extra: dev
Requires-Dist: basedpyright; extra == "dev"
Requires-Dist: numpy; extra == "dev"
Requires-Dist: pytest; extra == "dev"
Requires-Dist: qiskit-aer; extra == "dev"
Requires-Dist: ruff; extra == "dev"
Requires-Dist: cirq-core; extra == "dev"
Requires-Dist: qiskit; extra == "dev"
Requires-Dist: sympy; extra == "dev"
Dynamic: home-page
Dynamic: provides-extra
Dynamic: requires-dist
Dynamic: requires-python
Dynamic: summary
